unit/__init__.py
unit/_testbase.py
unit/app.py
unit/exceptions.py
unit/message.py
unit/parser.py
unit/protocols.py
unit/router.py
unit/utils.py
Unit-0.2.2.dist-info/LICENSE
Unit-0.2.2.dist-info/METADATA
Unit-0.2.2.dist-info/WHEEL
Unit-0.2.2.dist-info/top_level.txt
Unit-0.2.2.dist-info/RECORD
