Metadata-Version: 1.2
Name: Unit
Version: 0.2.2
Summary: An asynchronous web framework written in Python.
Home-page: https://github.com/jiangwwei/unit
Author: Jiang Wei
Author-email: jiangweiaz@gmail.com
License: Apache License, Version 2.0
Platform: POSIX
Classifier: Development Status :: 3 - Alpha
Classifier: Intended Audience :: Developers
Classifier: Environment :: Web Environment
Classifier: License :: OSI Approved :: Apache Software License
Classifier: Programming Language :: Python :: 3 :: Only
Classifier: Programming Language :: Python :: 3.5
Classifier: Programming Language :: Python :: 3.6
Classifier: Operating System :: POSIX
Classifier: Operating System :: MacOS :: MacOS X
Requires-Python: >=3.5
